slidecraft_mcp/__init__.py
slidecraft_mcp/server.py
slidecraft_mcp/server_fast.py
slidecraft_mcp-0.1.0.dist-info/METADATA
slidecraft_mcp-0.1.0.dist-info/WHEEL
slidecraft_mcp-0.1.0.dist-info/entry_points.txt
slidecraft_mcp-0.1.0.dist-info/licenses/LICENSE
slidecraft_mcp-0.1.0.dist-info/RECORD
