Metadata-Version: 2.4
Name: slidecraft-mcp
Version: 0.1.0
Summary: SlideCraft MCP - Lightweight presentation generator with LLM-powered content creation
Project-URL: Homepage, https://github.com/slidecraft-mcp/slidecraft-mcp
Project-URL: Repository, https://github.com/slidecraft-mcp/slidecraft-mcp
Project-URL: Issues, https://github.com/slidecraft-mcp/slidecraft-mcp/issues
Project-URL: Documentation, https://github.com/slidecraft-mcp/slidecraft-mcp#readme
Author-email: SlideCraft MCP Team <team@slidecraft-mcp.dev>
License-Expression: MIT
License-File: LICENSE
Keywords: ascii,lightweight,llm,mcp,powerpoint,presentations
Classifier: Development Status :: 4 - Beta
Classifier: Intended Audience :: Developers
Classifier: License :: OSI Approved :: MIT License
Classifier: Programming Language :: Python :: 3
Classifier: Programming Language :: Python :: 3.13
Classifier: Topic :: Office/Business :: Office Suites
Classifier: Topic :: Software Development :: Libraries :: Python Modules
Requires-Python: >=3.13
Requires-Dist: mcp>=1.13.0
